Workbook

Sheet Parametros
A1: HAVEN — Domótica por unidad: parámetros y supuestos
A3: Parámetro | B3: Valor | C3: Nota
A4: TC BNA oficial (ARS/USD) | B4: 1520 | C4: Referencia interna, no afecta estos cálculos (todo en USD)
A5: Margen — Integración Tecnológica (Base) | B5: 0.27 | C5: 27% fijo sobre costo — excepción de pricing de HAVEN, ya vigente en el proyecto
A6: Margen — Domótica (Upgrades 1 y 2, con Calypso) | B6: 0.2 | C6: 20% sobre costo — pedido explícito de Agustín para incentivar adopción
A7: Margen — B2C remarque | B7: 0.35 | C7: Remarque estándar Nova Domus cuando no hay precio de referencia
A8: Margen — B2C descuento | B8: 0.05 | C8: 5% off sobre el precio sugerido (regla B2C estándar)
A9: Margen — B2C efectivo (multiplicador sobre costo c/IVA) | B9: =(1+B7)*(1-B8)-1 | C9: Aplica a Upgrade 3 (standalone, sin Calypso)
A10: Valor de venta promedio por unidad (Torre 1, blended) | B10: 86667 | C10: Fuente: INCIDENCIA_POR_TORRE_v8_1.md
A11: Unidades 1 dormitorio (Torre 1) | B11: 73
A12: Unidades 2 dormitorios (Torre 1) | B12: 11
A13: Total unidades Torre 1 | B13: =B11+B12
A14: AC — unidades de control por depto 1D | B14: 2 | C14: Sensibo por split — 1 en estar + 1 en dormitorio
A15: AC — unidades de control por depto 2D | B15: 3 | C15: Sensibo por split — 1 en estar + 2 en dormitorios
A16: Cortinas — motores por unidad (todas) | B16: 3 | C16: Shelly Plus 2PM por motor (control bidireccional)
A17: Iluminación — relés Shelly por unidad (promedio) | B17: 2 | C17: Real: 179 relés/84u = 2,13 — se usa 2 como aproximación para upgrades por unidad
A18: Margen — Upgrade 3 (definido por Agustín, no B2C estándar) | B18: 0.35 | C18: Reemplaza el B2C efectivo (28,25%) — decisión explícita para ampliar la brecha vs. Camino A/B
A19: Recargo MO retrofit (instalación individual post-obra, Upgrade 3) | B19: 0.4 | C19: Visita única, coordinación aparte, unidad ya terminada (canaletas a la vista) — vs. instalación en bloque durante la obra
A20: Visita técnica inicial (Upgrade 3, fee fijo por unidad) | B20: 180 | C20: No existe en instalación en bloque (se amortiza entre 84 unidades); en un retrofit individual es un costo real aparte

Sheet Dispositivos
A1: Catálogo de dispositivos considerados (precio neto real de inventario Nova Domus)
A3: # | B3: Dispositivo | C3: Marca/SKU | D3: Precio sin IVA (USD) | E3: IVA % | F3: Tarifa MO (USD, tarifario ND) | G3: sku_mo | H3: Uso en este esquema
A4: 1 | B4: Cerradura digital Yale KIT YMC420 + HUB | C4: YALE / 16784 | D4: 232.24 | E4: 0.21 | F4: 100 | G4: MO-ACC-PORT* | H4: Base — todas las unidades
A5: 2 | B5: Pantalla básica Hikvision DS-KH6110-WE1 (4,3", PoE, no Android) | C5: HIKVISION / DS-KH6110-WE1 | D5: 127 | E5: 0.21 | F5: 117.31 | G5: MO-ACC-PORT | H5: Base — todas las unidades
A6: 3 | B6: Pantalla Android Hikvision DS-KH9310-WTE1(B) (7", PoE, Hik-Connect) | C6: HIKVISION / DS-KH9310-WTE1(B) | D6: 394 | E6: 0.21 | F6: 117.31 | G6: MO-ACC-PORT | H6: Upgrade 1 — reemplaza a la básica
A7: 4 | B7: Relé Shelly 1PM Mini Gen4 (iluminación) | C7: SHELLY / 387 | D7: 23.36 | E7: 0.21 | F7: 49.79 | G7: MO-DOM-MULTI* | H7: Upgrade 1 — iluminación
A8: 5 | B8: Dimmer Shelly Gen4 | C8: SHELLY / 358 | D8: 54 | E8: 0.21 | F8: 59.74 | G8: MO-DOM-DIM | H8: Upgrade 2 — control de intensidad
A9: 6 | B9: Sensor apertura Shelly BLU Door/Window ZB (Homiq) | C9: SHELLY / 659 | D9: 24.9 | E9: 0.21 | F9: 27.82 | G9: MO-DOM-MULTI* | H9: Upgrade 2 — sensor de apertura
A10: 7 | B10: Sensibo Air Smart AC Controller B2B (control de aire acondicionado) | C10: SENSIBO / 325 | D10: 174.74 | E10: 0.21 | F10: 30.1 | G10: MO-CLI-SPLIT | H10: Upgrade 2 — control de AC, x2 (1D) o x3 (2D)
A11: 8 | B11: Shelly Plus 2PM Gen4 (control de motor de cortina) | C11: SHELLY / 357 | D11: 33.9 | E11: 0.21 | F11: 69.7 | G11: MO-DOM-MULTI | H11: Upgrade 2 — cortinas, x3 por unidad
A12: 9 | B12: Home Assistant Green (hub standalone) | C12: HOME ASSISTANT / 209 | D12: 345 | E12: 0.21 | F12: 95.22 | G12: MO-INF-RACK* | H12: Upgrade 3 — infraestructura propia del cliente
A13: 10 | B13: Shelly Wall Display (7", chica — no XL) | C13: SHELLY / 371 | D13: 204.37 | E13: 0.21 | F13: 85 | G13: MO-DOM-CORE | H13: Upgrade 3 — infraestructura propia del cliente
A14: 11 | B14: Router TP-Link Archer AX55 (WiFi 6, dual band) | C14: TP-Link / ARCHER AX55 | D14: 76.35 | E14: 0.105 | F14: 69.7 | G14: MO-RED-SW* | H14: Upgrade 3 — infraestructura propia del cliente
A17: * Tarifa MO estimada por analogía con la categoría más cercana del tarifario ND — no tiene sku_mo propio cargado todavía, revisar antes de cotizar en firme.

Sheet Comparativa
A1: COMPARATIVA — progresión acumulativa por camino, USD por unidad
A2: Cada fila es acumulativa (incluye todo lo de arriba). Fórmulas enlazadas — cambiá un margen en Parametros y recalcula todo.
A4: Camino | B4: Qué incluye (acumulado) | C4: 1 Dormitorio | D4: 2 Dormitorios | E4: Quién paga / decide
A5: Base | B5: Cerradura + pantalla básica (mandatorio, Integración Tecnológica) | C5: =Item1_Base!K9 | D5: =Item1_Base!K9 | E5: Calypso — siempre
A6: Upgrade 1A | B6: Base + swap de pantalla a Android + iluminación (Calypso, bulk x84) | C6: =C5+Item2_Upg1_Calypso!K10 | D6: =D5+Item2_Upg1_Calypso!K10 | E6: Calypso decide para las 84 unidades
A7: Upgrade 2A | B7: Upgrade 1A + dimmer/sensor/AC/cortinas (cliente, sobre lo que ya puso Calypso) | C7: =C6+Item4_Upg2_Cliente!K10 | D7: =D6+Item4_Upg2_Cliente!K20 | E7: Cliente decide, ya con Upgrade1A puesto
A8: Upgrade 1B | B8: Base + pantalla Android completa + iluminación (cliente, individual, sin resta) | C8: =C5+Item3_Upg1_Cliente!K7 | D8: =D5+Item3_Upg1_Cliente!K7 | E8: Cliente decide, Calypso no hizo Upgrade1
A9: Upgrade 2B | B9: Upgrade 1B + dimmer/sensor/AC/cortinas (mismo valor estándar que 2A) | C9: =C8+Item4_Upg2_Cliente!K10 | D9: =D8+Item4_Upg2_Cliente!K20 | E9: Cliente decide, arma todo por su cuenta
A10: Camino B (sin desperdicio) | B10: Si Calypso hubiera puesto directo la pantalla Android (sin pasar por la básica) — sin desperdiciar esa compra | C10: =Item1_Base!K5/84+Item3_Upg1_Cliente!K7+Item4_Upg2_Cliente!K10 | D10: =Item1_Base!K5/84+Item3_Upg1_Cliente!K7+Item4_Upg2_Cliente!K20 | E10: Hipotético — no es el camino real (Calypso ya decidió básica para todos), sirve de referencia
A11: Upgrade 3 | B11: Standalone completo: HA Green + Wall Display + Router + todo el kit (margen 35%) | C11: =Item5_Upg3_Standalone!K16 | D11: =Item5_Upg3_Standalone!K32 | E11: Cliente paga todo, sin Integración Tecnológica de Calypso
A13: Diferencia Upgrade 3 vs. Upgrade 2A | C13: =C11-C7 | D13: =D11-D7
A14: Diferencia Upgrade 3 vs. Upgrade 2B | C14: =C11-C9 | D14: =D11-D9
A15: % Upgrade 3 sobre Upgrade 2B | C15: =C11/C9-1 | D15: =D11/D9-1
A18: Nota: filas resaltadas (Upgrade 2A, 2B, 3) son los 3 puntos de comparación finales relevantes para la decisión de Calypso/cliente.

Sheet Item1_Base
A1: ITEM 1 — BASE: Integración Tecnológica + Inmótica (Calypso, mandatorio, x84 unidades)
A2: Margen aplicado: Parametros!$B$5 (27% Integración Tecnológica)
A4: Dispositivo | B4: Cant. | C4: Precio s/IVA | D4: IVA% | E4: Precio c/IVA (costo) | F4: Margen | G4: Precio venta unit. | H4: Subtotal equipo | I4: MO unit. | J4: Subtotal MO | K4: TOTAL línea
A5: Cerradura Yale KIT YMC420 | B5: 84 | C5: =Dispositivos!D4 | D5: =Dispositivos!E4 | E5: =C5*(1+D5) | F5: =Parametros!$B$5 | G5: =E5*(1+F5) | H5: =G5*B5 | I5: =Dispositivos!F4 | J5: =I5*B5 | K5: =H5+J5
A6: Pantalla básica DS-KH6110-WE1 | B6: 84 | C6: =Dispositivos!D5 | D6: =Dispositivos!E5 | E6: =C6*(1+D6) | F6: =Parametros!$B$5 | G6: =E6*(1+F6) | H6: =G6*B6 | I6: =Dispositivos!F5 | J6: =I6*B6 | K6: =H6+J6
A7: TOTAL Item 1 (84 unidades) | H7: =SUM(H5:H6) | J7: =SUM(J5:J6) | K7: =H7+J7
A9: Por unidad: | H9: =H7/84 | J9: =J7/84 | K9: =K7/84 | L9: =+K9+Item2_Upg1_Calypso!K10
A11: Incidencia por unidad sobre valor de venta: | K11: =K9/Parametros!$B$10

Sheet Item2_Upg1_Calypso
A1: ITEM 2 — UPGRADE 1 PARA CALYPSO: swap de pantalla + iluminación (bulk, x84 unidades)
A2: Margen aplicado: Parametros!$B$6 (20% Domótica)
A4: Dispositivo | B4: Cant. | C4: Precio s/IVA | D4: IVA% | E4: Precio c/IVA (costo) | F4: Margen | G4: Precio venta unit. | H4: Subtotal equipo | I4: MO unit. | J4: Subtotal MO | K4: TOTAL línea
A5: (-) Pantalla básica DS-KH6110-WE1 [se retira] | B5: 84 | C5: =Dispositivos!D5 | D5: =Dispositivos!E5 | E5: =C5*(1+D5) | F5: =Parametros!$B$6 | G5: =E5*(1+F5) | H5: =-G5*B5 | I5: =Dispositivos!F5 | J5: =-I5*B5 | K5: =H5+J5
A6: (+) Pantalla Android DS-KH9310-WTE1(B) [reemplaza] | B6: 84 | C6: =Dispositivos!D6 | D6: =Dispositivos!E6 | E6: =C6*(1+D6) | F6: =Parametros!$B$6 | G6: =E6*(1+F6) | H6: =G6*B6 | I6: =Dispositivos!F6 | J6: =I6*B6 | K6: =H6+J6
A7: (+) Relé Shelly 1PM Mini Gen4 (iluminación, ~2,13/u) | B7: 179 | C7: =Dispositivos!D7 | D7: =Dispositivos!E7 | E7: =C7*(1+D7) | F7: =Parametros!$B$6 | G7: =E7*(1+F7) | H7: =G7*B7 | I7: =Dispositivos!F7 | J7: =I7*B7 | K7: =H7+J7
A8: TOTAL Item 2 (84 unidades) | H8: =SUM(H5:H7) | J8: =SUM(J5:J7) | K8: =H8+J8
A10: Por unidad: | K10: =K8/84
A12: Incidencia por unidad: | K12: =K10/Parametros!$B$10

Sheet Item3_Upg1_Cliente
A1: ITEM 3 — UPGRADE 1 PARA EL CLIENTE: pantalla completa (sin descuento) + iluminación (individual, por unidad)
A2: Margen aplicado: Parametros!$B$6 (20% Domótica)
A4: Dispositivo | B4: Cant. | C4: Precio s/IVA | D4: IVA% | E4: Precio c/IVA (costo) | F4: Margen | G4: Precio venta unit. | H4: Subtotal equipo | I4: MO unit. | J4: Subtotal MO | K4: TOTAL línea
A5: Pantalla Android DS-KH9310-WTE1(B) (completa, no se resta la básica) | B5: 1 | C5: =Dispositivos!D6 | D5: =Dispositivos!E6 | E5: =C5*(1+D5) | F5: =Parametros!$B$6 | G5: =E5*(1+F5) | H5: =G5*B5 | I5: =Dispositivos!F6 | J5: =I5*B5 | K5: =H5+J5
A6: Relé Shelly 1PM Mini Gen4 (iluminación, ~2/u) | B6: 2 | C6: =Dispositivos!D7 | D6: =Dispositivos!E7 | E6: =C6*(1+D6) | F6: =Parametros!$B$6 | G6: =E6*(1+F6) | H6: =G6*B6 | I6: =Dispositivos!F7 | J6: =I6*B6 | K6: =H6+J6
A7: TOTAL Item 3 (por unidad) | H7: =SUM(H5:H6) | J7: =SUM(J5:J6) | K7: =H7+J7
A9: Incidencia por unidad: | K9: =K7/Parametros!$B$10

Sheet Item4_Upg2_Cliente
A1: ITEM 4 — UPGRADE 2 PARA EL CLIENTE: dimmer + sensor + control de AC + cortinas (requiere Upgrade 1 ya puesto)
A2: Margen aplicado: Parametros!$B$6 (20%)
A4: --- Tipología 1 Dormitorio ---
A5: Dispositivo | B5: Cant. | C5: Precio s/IVA | D5: IVA% | E5: Precio c/IVA | F5: Margen | G5: Precio venta unit. | H5: Subtotal equipo | I5: MO unit. | J5: Subtotal MO | K5: TOTAL línea
A6: Dimmer Shelly Gen4 | B6: 1 | C6: =Dispositivos!D8 | D6: =Dispositivos!E8 | E6: =C6*(1+D6) | F6: =Parametros!$B$6 | G6: =E6*(1+F6) | H6: =G6*B6 | I6: =Dispositivos!F8 | J6: =I6*B6 | K6: =H6+J6
A7: Sensor apertura BLU Door/Window ZB | B7: 1 | C7: =Dispositivos!D9 | D7: =Dispositivos!E9 | E7: =C7*(1+D7) | F7: =Parametros!$B$6 | G7: =E7*(1+F7) | H7: =G7*B7 | I7: =Dispositivos!F9 | J7: =I7*B7 | K7: =H7+J7
A8: Sensibo Air B2B (control AC x2) | B8: 2 | C8: =Dispositivos!D10 | D8: =Dispositivos!E10 | E8: =C8*(1+D8) | F8: =Parametros!$B$6 | G8: =E8*(1+F8) | H8: =G8*B8 | I8: =Dispositivos!F10 | J8: =I8*B8 | K8: =H8+J8
A9: Shelly Plus 2PM Gen4 (cortinas x3) | B9: 3 | C9: =Dispositivos!D11 | D9: =Dispositivos!E11 | E9: =C9*(1+D9) | F9: =Parametros!$B$6 | G9: =E9*(1+F9) | H9: =G9*B9 | I9: =Dispositivos!F11 | J9: =I9*B9 | K9: =H9+J9
A10: TOTAL 1 Dormitorio | H10: =SUM(H6:H9) | J10: =SUM(J6:J9) | K10: =H10+J10
A12: Incidencia por unidad: | K12: =K10/Parametros!$B$10
A14: --- Tipología 2 Dormitorios ---
A15: Dispositivo | B15: Cant. | C15: Precio s/IVA | D15: IVA% | E15: Precio c/IVA | F15: Margen | G15: Precio venta unit. | H15: Subtotal equipo | I15: MO unit. | J15: Subtotal MO | K15: TOTAL línea
A16: Dimmer Shelly Gen4 | B16: 1 | C16: =Dispositivos!D8 | D16: =Dispositivos!E8 | E16: =C16*(1+D16) | F16: =Parametros!$B$6 | G16: =E16*(1+F16) | H16: =G16*B16 | I16: =Dispositivos!F8 | J16: =I16*B16 | K16: =H16+J16
A17: Sensor apertura BLU Door/Window ZB | B17: 1 | C17: =Dispositivos!D9 | D17: =Dispositivos!E9 | E17: =C17*(1+D17) | F17: =Parametros!$B$6 | G17: =E17*(1+F17) | H17: =G17*B17 | I17: =Dispositivos!F9 | J17: =I17*B17 | K17: =H17+J17
A18: Sensibo Air B2B (control AC x3) | B18: 3 | C18: =Dispositivos!D10 | D18: =Dispositivos!E10 | E18: =C18*(1+D18) | F18: =Parametros!$B$6 | G18: =E18*(1+F18) | H18: =G18*B18 | I18: =Dispositivos!F10 | J18: =I18*B18 | K18: =H18+J18
A19: Shelly Plus 2PM Gen4 (cortinas x3) | B19: 3 | C19: =Dispositivos!D11 | D19: =Dispositivos!E11 | E19: =C19*(1+D19) | F19: =Parametros!$B$6 | G19: =E19*(1+F19) | H19: =G19*B19 | I19: =Dispositivos!F11 | J19: =I19*B19 | K19: =H19+J19
A20: TOTAL 2 Dormitorios | H20: =SUM(H16:H19) | J20: =SUM(J16:J19) | K20: =H20+J20
A22: Incidencia por unidad: | K22: =K20/Parametros!$B$10

Sheet Item5_Upg3_Standalone
A1: ITEM 5 — UPGRADE 3 STANDALONE: sin Integración Tecnológica ni Inmótica de Calypso (tipo Panoramic)
A2: Margen equipo: Parametros!$B$18 (35%) | Recargo MO retrofit: Parametros!$B$19 (+40%) | Visita técnica: Parametros!$B$20 (fee fijo)
A4: --- Tipología 1 Dormitorio ---
A5: Dispositivo | B5: Cant. | C5: Precio s/IVA | D5: IVA% | E5: Precio c/IVA | F5: Margen | G5: Precio venta unit. | H5: Subtotal equipo | I5: MO unit. (+recargo) | J5: Subtotal MO | K5: TOTAL línea
A6: Cerradura digital Yale KIT YMC420 + HUB (standalone) | B6: 1 | C6: =Dispositivos!D4 | D6: =Dispositivos!E4 | E6: =C6*(1+D6) | F6: =Parametros!$B$18 | G6: =E6*(1+F6) | H6: =G6*B6 | I6: =Dispositivos!F4*(1+Parametros!$B$19) | J6: =I6*B6 | K6: =H6+J6
A7: Shelly Wall Display (chica, standalone) | B7: 1 | C7: =Dispositivos!D13 | D7: =Dispositivos!E13 | E7: =C7*(1+D7) | F7: =Parametros!$B$18 | G7: =E7*(1+F7) | H7: =G7*B7 | I7: =Dispositivos!F13*(1+Parametros!$B$19) | J7: =I7*B7 | K7: =H7+J7
A8: Home Assistant Green (standalone) | B8: 1 | C8: =Dispositivos!D12 | D8: =Dispositivos!E12 | E8: =C8*(1+D8) | F8: =Parametros!$B$18 | G8: =E8*(1+F8) | H8: =G8*B8 | I8: =Dispositivos!F12*(1+Parametros!$B$19) | J8: =I8*B8 | K8: =H8+J8
A9: Router TP-Link Archer AX55 (standalone) | B9: 1 | C9: =Dispositivos!D14 | D9: =Dispositivos!E14 | E9: =C9*(1+D9) | F9: =Parametros!$B$18 | G9: =E9*(1+F9) | H9: =G9*B9 | I9: =Dispositivos!F14*(1+Parametros!$B$19) | J9: =I9*B9 | K9: =H9+J9
A10: Relé Shelly 1PM Mini Gen4 (iluminación, ~2/u) | B10: 2 | C10: =Dispositivos!D7 | D10: =Dispositivos!E7 | E10: =C10*(1+D10) | F10: =Parametros!$B$18 | G10: =E10*(1+F10) | H10: =G10*B10 | I10: =Dispositivos!F7*(1+Parametros!$B$19) | J10: =I10*B10 | K10: =H10+J10
A11: Dimmer Shelly Gen4 | B11: 1 | C11: =Dispositivos!D8 | D11: =Dispositivos!E8 | E11: =C11*(1+D11) | F11: =Parametros!$B$18 | G11: =E11*(1+F11) | H11: =G11*B11 | I11: =Dispositivos!F8*(1+Parametros!$B$19) | J11: =I11*B11 | K11: =H11+J11
A12: Sensor apertura BLU Door/Window ZB | B12: 1 | C12: =Dispositivos!D9 | D12: =Dispositivos!E9 | E12: =C12*(1+D12) | F12: =Parametros!$B$18 | G12: =E12*(1+F12) | H12: =G12*B12 | I12: =Dispositivos!F9*(1+Parametros!$B$19) | J12: =I12*B12 | K12: =H12+J12
A13: Sensibo Air B2B (control AC x2) | B13: 2 | C13: =Dispositivos!D10 | D13: =Dispositivos!E10 | E13: =C13*(1+D13) | F13: =Parametros!$B$18 | G13: =E13*(1+F13) | H13: =G13*B13 | I13: =Dispositivos!F10*(1+Parametros!$B$19) | J13: =I13*B13 | K13: =H13+J13
A14: Shelly Plus 2PM Gen4 (cortinas x3) | B14: 3 | C14: =Dispositivos!D11 | D14: =Dispositivos!E11 | E14: =C14*(1+D14) | F14: =Parametros!$B$18 | G14: =E14*(1+F14) | H14: =G14*B14 | I14: =Dispositivos!F11*(1+Parametros!$B$19) | J14: =I14*B14 | K14: =H14+J14
A15: Visita técnica inicial (fee fijo, no existe en instalación en bloque) | B15: 1 | H15: 0 | J15: =Parametros!$B$20 | K15: =H15+J15
A16: TOTAL 1 Dormitorio | H16: =SUM(H6:H15) | J16: =SUM(J6:J15) | K16: =H16+J16
A18: Incidencia por unidad: | K18: =K16/Parametros!$B$10
A20: --- Tipología 2 Dormitorios ---
A21: Dispositivo | B21: Cant. | C21: Precio s/IVA | D21: IVA% | E21: Precio c/IVA | F21: Margen | G21: Precio venta unit. | H21: Subtotal equipo | I21: MO unit. (+recargo) | J21: Subtotal MO | K21: TOTAL línea
A22: Cerradura digital Yale KIT YMC420 + HUB (standalone) | B22: 1 | C22: =Dispositivos!D4 | D22: =Dispositivos!E4 | E22: =C22*(1+D22) | F22: =Parametros!$B$18 | G22: =E22*(1+F22) | H22: =G22*B22 | I22: =Dispositivos!F4*(1+Parametros!$B$19) | J22: =I22*B22 | K22: =H22+J22
A23: Shelly Wall Display (chica, standalone) | B23: 1 | C23: =Dispositivos!D13 | D23: =Dispositivos!E13 | E23: =C23*(1+D23) | F23: =Parametros!$B$18 | G23: =E23*(1+F23) | H23: =G23*B23 | I23: =Dispositivos!F13*(1+Parametros!$B$19) | J23: =I23*B23 | K23: =H23+J23
A24: Home Assistant Green (standalone) | B24: 1 | C24: =Dispositivos!D12 | D24: =Dispositivos!E12 | E24: =C24*(1+D24) | F24: =Parametros!$B$18 | G24: =E24*(1+F24) | H24: =G24*B24 | I24: =Dispositivos!F12*(1+Parametros!$B$19) | J24: =I24*B24 | K24: =H24+J24
A25: Router TP-Link Archer AX55 (standalone) | B25: 1 | C25: =Dispositivos!D14 | D25: =Dispositivos!E14 | E25: =C25*(1+D25) | F25: =Parametros!$B$18 | G25: =E25*(1+F25) | H25: =G25*B25 | I25: =Dispositivos!F14*(1+Parametros!$B$19) | J25: =I25*B25 | K25: =H25+J25
A26: Relé Shelly 1PM Mini Gen4 (iluminación, ~2/u) | B26: 2 | C26: =Dispositivos!D7 | D26: =Dispositivos!E7 | E26: =C26*(1+D26) | F26: =Parametros!$B$18 | G26: =E26*(1+F26) | H26: =G26*B26 | I26: =Dispositivos!F7*(1+Parametros!$B$19) | J26: =I26*B26 | K26: =H26+J26
A27: Dimmer Shelly Gen4 | B27: 1 | C27: =Dispositivos!D8 | D27: =Dispositivos!E8 | E27: =C27*(1+D27) | F27: =Parametros!$B$18 | G27: =E27*(1+F27) | H27: =G27*B27 | I27: =Dispositivos!F8*(1+Parametros!$B$19) | J27: =I27*B27 | K27: =H27+J27
A28: Sensor apertura BLU Door/Window ZB | B28: 1 | C28: =Dispositivos!D9 | D28: =Dispositivos!E9 | E28: =C28*(1+D28) | F28: =Parametros!$B$18 | G28: =E28*(1+F28) | H28: =G28*B28 | I28: =Dispositivos!F9*(1+Parametros!$B$19) | J28: =I28*B28 | K28: =H28+J28
A29: Sensibo Air B2B (control AC x3) | B29: 3 | C29: =Dispositivos!D10 | D29: =Dispositivos!E10 | E29: =C29*(1+D29) | F29: =Parametros!$B$18 | G29: =E29*(1+F29) | H29: =G29*B29 | I29: =Dispositivos!F10*(1+Parametros!$B$19) | J29: =I29*B29 | K29: =H29+J29
A30: Shelly Plus 2PM Gen4 (cortinas x3) | B30: 3 | C30: =Dispositivos!D11 | D30: =Dispositivos!E11 | E30: =C30*(1+D30) | F30: =Parametros!$B$18 | G30: =E30*(1+F30) | H30: =G30*B30 | I30: =Dispositivos!F11*(1+Parametros!$B$19) | J30: =I30*B30 | K30: =H30+J30
A31: Visita técnica inicial (fee fijo, no existe en instalación en bloque) | B31: 1 | H31: 0 | J31: =Parametros!$B$20 | K31: =H31+J31
A32: TOTAL 2 Dormitorios | H32: =SUM(H22:H31) | J32: =SUM(J22:J31) | K32: =H32+J32
A34: Incidencia por unidad: | K34: =K32/Parametros!$B$10
